{
  "__comments": [
    "WARNING: All changes should be made to the file with the name Custom",
    "in the title. Changes made to the Generated file will be overwritten.",
    "",
    "This file defines input and output pairs for auto-generating recipes",
    "for the Chopping Block.",
    "",
    "Entries are in the format (input): (output)",
    "Entry item strings are in the format: (domain):(path):(meta)"
  ],
  "entries": {
    "aoa3:achony_log:0": "aoa3:achony_planks:0",
    "aoa3:achony_planks:0": "aoa3:achony_slab:0",
    "aoa3:blood_log:0": "aoa3:bloodwood_planks:0",
    "aoa3:bloodwood_planks:0": "aoa3:bloodwood_slab:0",
    "aoa3:churry_log:0": "aoa3:churry_planks:0",
    "aoa3:churry_planks:0": "aoa3:churry_slab:0",
    "aoa3:creep_log:0": "aoa3:creep_planks:0",
    "aoa3:creep_planks:0": "aoa3:creep_slab:0",
    "aoa3:cycade_log:0": "aoa3:cycade_planks:0",
    "aoa3:cycade_planks:0": "aoa3:cycade_slab:0",
    "aoa3:dawn_log:0": "aoa3:dawnwood_planks:0",
    "aoa3:dawnwood_planks:0": "aoa3:dawnwood_slab:0",
    "aoa3:domiguous_log:0": "aoa3:domiguous_planks:0",
    "aoa3:domiguous_planks:0": "aoa3:domiguous_slab:0",
    "aoa3:eucadon_log:0": "aoa3:eucadon_planks:0",
    "aoa3:eucadon_planks:0": "aoa3:eucadon_slab:0",
    "aoa3:eyeball_log:0": "aoa3:bloodwood_planks:0",
    "aoa3:haunted_eye_log:0": "aoa3:hauntedwood_planks:0",
    "aoa3:haunted_eyes_log:0": "aoa3:hauntedwood_planks:0",
    "aoa3:haunted_flashing_log:0": "aoa3:hauntedwood_planks:0",
    "aoa3:haunted_log:0": "aoa3:hauntedwood_planks:0",
    "aoa3:haunted_purpling_log:0": "aoa3:hauntedwood_planks:0",
    "aoa3:iro_log:0": "aoa3:irowood_planks:0",
    "aoa3:irowood_planks:0": "aoa3:irowood_slab:0",
    "aoa3:lucalus_log:0": "aoa3:lucalus_planks:0",
    "aoa3:lucalus_planks:0": "aoa3:lucalus_slab:0",
    "aoa3:lunide_log:0": "aoa3:lunide_planks:0",
    "aoa3:lunide_planks:0": "aoa3:lunide_slab:0",
    "aoa3:melumia_log:0": "aoa3:melumia_planks:0",
    "aoa3:melumia_planks:0": "aoa3:melumia_slab:0",
    "aoa3:opollo_log:0": "aoa3:opollo_planks:0",
    "aoa3:opollo_planks:0": "aoa3:opollo_slab:0",
    "aoa3:runic_log:0": "aoa3:runic_planks:0",
    "aoa3:runic_planks:0": "aoa3:runic_slab:0",
    "aoa3:shadow_log:0": "aoa3:shadow_planks:0",
    "aoa3:shadow_planks:0": "aoa3:shadow_slab:0",
    "aoa3:shyre_log:0": "aoa3:shyre_planks:0",
    "aoa3:shyre_planks:0": "aoa3:shyre_slab:0",
    "aoa3:stranglewood_log:0": "aoa3:stranglewood_planks:0",
    "aoa3:stranglewood_planks:0": "aoa3:stranglewood_slab:0",
    "aoa3:toxic_log:0": "aoa3:toxicwood_planks:0",
    "aoa3:toxicwood_planks:0": "aoa3:toxicwood_slab:0",
    "cuisine:log:0": "cuisine:planks:0",
    "harvestcraft:pamcinnamon:0": "minecraft:planks:3",
    "harvestcraft:pammaple:0": "minecraft:planks:1",
    "harvestcraft:pampaperbark:0": "minecraft:planks:3",
    "minecraft:planks:0": "minecraft:wooden_slab:0",
    "minecraft:planks:1": "minecraft:wooden_slab:1",
    "minecraft:planks:2": "minecraft:wooden_slab:2",
    "minecraft:planks:3": "minecraft:wooden_slab:3",
    "minecraft:planks:4": "minecraft:wooden_slab:4",
    "minecraft:planks:5": "minecraft:wooden_slab:5",
    "mysticalworld:charred_log:0": "mysticalworld:charred_planks:0",
    "mysticalworld:charred_planks:0": "mysticalworld:charred_slab:0",
    "prodigytech:zorra_log:0": "prodigytech:zorra_planks:0",
    "randomthings:spectrelog:0": "randomthings:spectreplank:0",
    "roots:wildwood_log:0": "roots:wildwood_planks:0",
    "roots:wildwood_planks:0": "roots:wildwood_slab:0",
    "thaumcraft:log_greatwood:0": "thaumcraft:plank_greatwood:0",
    "thaumcraft:log_silverwood:0": "thaumcraft:plank_silverwood:0",
    "thaumcraft:plank_greatwood:0": "thaumcraft:slab_greatwood:0",
    "thaumcraft:plank_silverwood:0": "thaumcraft:slab_silverwood:0",
    "thebetweenlands:giant_root:0": "thebetweenlands:giant_root_planks:0",
    "thebetweenlands:giant_root_planks:0": "thebetweenlands:giant_root_plank_slab:0",
    "thebetweenlands:hearthgrove_planks:0": "thebetweenlands:hearthgrove_plank_slab:0",
    "thebetweenlands:log_rubber:0": "thebetweenlands:rubber_tree_planks:0",
    "thebetweenlands:nibbletwig_planks:0": "thebetweenlands:nibbletwig_plank_slab:0",
    "thebetweenlands:rubber_tree_planks:0": "thebetweenlands:rubber_tree_plank_slab:0",
    "thebetweenlands:weedwood_planks:0": "thebetweenlands:weedwood_plank_slab:0",
    "traverse:fir_log:0": "traverse:fir_planks:0",
    "traverse:fir_planks:0": "traverse:fir_slab:0"
  }
}